pagtest/LazyPy_Basic.py
pagtest/__init__.py
LazyPy_Basic-1.0.0.dist-info/METADATA
LazyPy_Basic-1.0.0.dist-info/WHEEL
LazyPy_Basic-1.0.0.dist-info/top_level.txt
LazyPy_Basic-1.0.0.dist-info/RECORD
